README.md
setup.py
zappy/__init__.py
zappy/base.py
zappy/zarr_util.py
zappy.egg-info/PKG-INFO
zappy.egg-info/SOURCES.txt
zappy.egg-info/dependency_links.txt
zappy.egg-info/top_level.txt
zappy/beam/__init__.py
zappy/beam/array.py
zappy/direct/__init__.py
zappy/direct/array.py
zappy/executor/__init__.py
zappy/executor/array.py
zappy/executor/dag.py
zappy/spark/__init__.py
zappy/spark/array.py